{
  "$schema" : "https://json-schema.org/draft/2020-12/schema",
  "type" : "object",
  "title" : "xorcery.yaml JSON Schema",
  "properties" : {
    "jars" : {
      "$ref" : "#/$defs/jars"
    },
    "graphql" : {
      "$ref" : "#/$defs/graphql"
    }
  },
  "$defs" : {
    "jars" : {
      "type" : "object",
      "additionalProperties" : false,
      "properties" : {
        "transmutejars" : {
          "type" : [ "array", "string" ],
          "items" : {
            "anyOf" : [ {
              "type" : "object",
              "additionalProperties" : false,
              "properties" : {
                "jar" : {
                  "type" : "string",
                  "default" : "graphqldomainevents",
                  "description" : "Default: graphqldomainevents",
                  "const" : "graphqldomainevents"
                },
                "name" : {
                  "type" : "string",
                  "default" : "graphqldomainevents",
                  "description" : "Default: graphqldomainevents"
                },
                "metadata" : {
                  "type" : "object",
                  "additionalProperties" : true,
                  "properties" : { }
                }
              }
            } ]
          }
        }
      }
    }
  }
}